datatrails_scitt_samples/.gitignore
datatrails_scitt_samples/__init__.py
datatrails_scitt_samples/cbor_header_labels.py
datatrails_scitt_samples/cose_cnf_key.py
datatrails_scitt_samples/cose_receipt_verification.py
datatrails_scitt_samples/cose_sign1message.py
datatrails_scitt_samples/dump_cbor.py
datatrails_scitt_samples/errors.py
datatrails_scitt_samples/statement_creation.py
datatrails_scitt_samples/statement_registration.py
datatrails_scitt_samples/artifacts/artifact.js
datatrails_scitt_samples/artifacts/package.json
datatrails_scitt_samples/artifacts/thedroid.json
datatrails_scitt_samples/datatrails/.gitignore
datatrails_scitt_samples/datatrails/__init__.py
datatrails_scitt_samples/datatrails/apitoken.py
datatrails_scitt_samples/datatrails/entryid.py
datatrails_scitt_samples/datatrails/envconfig.py
datatrails_scitt_samples/datatrails/eventpreimage.py
datatrails_scitt_samples/datatrails/servicecontext.py
datatrails_scitt_samples/datatrails/v3eventhash.py
datatrails_scitt_samples/mmriver/.gitignore
datatrails_scitt_samples/mmriver/algorithms.py
datatrails_scitt_samples/mmriver/decodeinclusionproof.py
datatrails_scitt_samples/mmriver/inclusionproof.py
datatrails_scitt_samples/scripts/.gitignore
datatrails_scitt_samples/scripts/__init__.py
datatrails_scitt_samples/scripts/check_operation_status.py
datatrails_scitt_samples/scripts/create_hashed_signed_statement.py
datatrails_scitt_samples/scripts/create_signed_statement.py
datatrails_scitt_samples/scripts/datatrails_event_info.py
datatrails_scitt_samples/scripts/fileaccess.py
datatrails_scitt_samples/scripts/generate_example_key.py
datatrails_scitt_samples/scripts/register_signed_statement.py
datatrails_scitt_samples/scripts/verify_receipt.py.disabled
datatrails_scitt_samples-0.0.1.dist-info/LICENSE
datatrails_scitt_samples-0.0.1.dist-info/METADATA
datatrails_scitt_samples-0.0.1.dist-info/WHEEL
datatrails_scitt_samples-0.0.1.dist-info/entry_points.txt
datatrails_scitt_samples-0.0.1.dist-info/top_level.txt
datatrails_scitt_samples-0.0.1.dist-info/RECORD
