Metadata-Version: 2.1
Name: datatrails-scitt-samples
Version: 0.0.1
Summary: DataTrails SCITT Examples
Home-page: https://github.com/datatrails/datatrails-scitt-samples
Author: DataTrails Inc.
Author-email: support@datatrails.ai
License: MIT
Project-URL: Source, https://github.com/datatrails/datatrails-scitt-samples
Project-URL: Tracker, https://github.com/datatrails/datatrails-scitt-samples/issues
Classifier: Development Status :: 3 - Alpha
Classifier: Environment :: Console
Classifier: Intended Audience :: Developers
Classifier: License :: OSI Approved :: MIT License
Classifier: Operating System :: POSIX :: Linux
Classifier: Programming Language :: Python :: 3.11
Classifier: Topic :: Utilities
License-File: LICENSE
